README.md
setup.py
plc800stg/__init__.py
plc800stg/billings.py
plc800stg/measure_events.py
plc800stg/profiles.py
plc800stg/utils.py
plc800stg.egg-info/PKG-INFO
plc800stg.egg-info/SOURCES.txt
plc800stg.egg-info/dependency_links.txt
plc800stg.egg-info/requires.txt
plc800stg.egg-info/top_level.txt