Metadata-Version: 1.0
Name: plc800stg
Version: 0.0.1
Summary: PLC800 STG
Home-page: https://github.com/gisce/plc800stg
Author: GISCE-TI, S.L.
Author-email: devel@gisce.net
License: MIT License
Platform: UNKNOWN
